factpages_py/__init__.py
factpages_py/analysis.py
factpages_py/client.py
factpages_py/columns.json
factpages_py/database.py
factpages_py/datasets.py
factpages_py/display.py
factpages_py/entities.py
factpages_py/entity_config.py
factpages_py/formatters.py
factpages_py/graph.py
factpages_py/parallel.py
factpages_py/schema.json
factpages_py/schema.py
factpages_py/supplementary.py
factpages_py/sync.py
factpages_py-0.1.28.dist-info/METADATA
factpages_py-0.1.28.dist-info/WHEEL
factpages_py-0.1.28.dist-info/RECORD
