Metadata-Version: 2.4
Name: factpages-py
Version: 0.1.28
Summary: Python library for Norwegian Petroleum Factpages data
Project-URL: Homepage, https://github.com/kkollsga/factpages-py
Project-URL: Documentation, https://github.com/kkollsga/factpages-py#readme
Project-URL: Repository, https://github.com/kkollsga/factpages-py.git
Project-URL: Issues, https://github.com/kkollsga/factpages-py/issues
Author: Norwegian Petroleum Data Community
License-Expression: MIT
Keywords: api,discovery,field,gas,ncs,norway,npd,offshore,oil,petroleum,sodir,wellbore
Classifier: Development Status :: 3 - Alpha
Classifier: Intended Audience :: Developers
Classifier: Intended Audience :: Science/Research
Classifier: License :: OSI Approved :: MIT License
Classifier: Operating System :: MacOS
Classifier: Operating System :: Microsoft :: Windows
Classifier: Operating System :: OS Independent
Classifier: Operating System :: POSIX :: Linux
Classifier: Programming Language :: Python :: 3
Classifier: Programming Language :: Python :: 3.9
Classifier: Programming Language :: Python :: 3.10
Classifier: Programming Language :: Python :: 3.11
Classifier: Programming Language :: Python :: 3.12
Classifier: Programming Language :: Python :: 3.13
Classifier: Topic :: Scientific/Engineering
Classifier: Topic :: Scientific/Engineering :: GIS
Requires-Python: >=3.9
Requires-Dist: openpyxl>=3.0.0
Requires-Dist: pandas>=1.5.0
Requires-Dist: pyarrow>=12.0.0
Requires-Dist: requests>=2.28.0
Requires-Dist: tqdm>=4.60.0
Provides-Extra: dev
Requires-Dist: black>=23.0; extra == 'dev'
Requires-Dist: mypy>=1.0; extra == 'dev'
Requires-Dist: pytest-cov>=4.0; extra == 'dev'
Requires-Dist: pytest>=7.0; extra == 'dev'
Requires-Dist: ruff>=0.1.0; extra == 'dev'
Provides-Extra: geo
Requires-Dist: geopandas>=0.12.0; extra == 'geo'
Requires-Dist: shapely>=2.0.0; extra == 'geo'
